setup.py
pyexCakeCrusher/__init__.py
pyexCakeCrusher.egg-info/PKG-INFO
pyexCakeCrusher.egg-info/SOURCES.txt
pyexCakeCrusher.egg-info/dependency_links.txt
pyexCakeCrusher.egg-info/requires.txt
pyexCakeCrusher.egg-info/top_level.txt